<?xml version="1.0" encoding="UTF-8"?>
<objects serializationModel="Studio.02.02.00">
	<object class="AudioFile" id="{ac5add0d-9176-4770-b9ab-02cf358a6758}">
		<property name="assetPath">
			<value>SFX/IdentifyStutter/confused_cat_hiss.mp3</value>
		</property>
		<property name="frequencyInKHz">
			<value>48</value>
		</property>
		<property name="channelCount">
			<value>2</value>
		</property>
		<property name="length">
			<value>3.8639999999999999</value>
		</property>
		<relationship name="masterAssetFolder">
			<destination>{ff6d5952-8dd7-4ae2-8ab5-7b451ca5812d}</destination>
		</relationship>
	</object>
</objects>
