{"dID":55951,"playerDiags":2,"actionNodes":2,"startPoint":0,"loadTag":"","previewPanning":false,"autosave":true,"locEdit":true,"showSettings":true,"pd_isp_0":false,"pd_rect_0":[-390,-190],"pd_comSize_0":3,"pd_ID_0":0,"pd_pTag_0":"Narrador","pd_sprite_0":"Assets/VIDE/Data/Resources/Sprites/narrator.png","pd_expand_0":true,"pd_vars0":0,"pd_0_com_0iSet":-1,"pd_0_com_0oAns":-1,"pd_0_com_0oAct":0,"pd_0_com_0text":"A nossa hist\u00f3ria come\u00e7a com a tua ida para a casa da av\u00f3 no \u00ednicio das f\u00e9rias de ver\u00e3o.","pd_0_com_0extraD":"ExtraData","pd_0_com_0showmore":false,"pd_0_com_0visible":true,"pd_0_com_0audio":"","pd_0_com_0sprite":"","pd_0_com_1iSet":0,"pd_0_com_1oAns":-1,"pd_0_com_1oAct":-1,"pd_0_com_1text":"Eu sou o narrador, deus todo poderoso que te acompanha ao longo desta hist\u00f3ria","pd_0_com_1extraD":"ExtraData","pd_0_com_1showmore":false,"pd_0_com_1visible":true,"pd_0_com_1audio":"","pd_0_com_1sprite":"","pd_0_com_2iSet":0,"pd_0_com_2oAns":-1,"pd_0_com_2oAct":-1,"pd_0_com_2text":"Mas antes de come\u00e7armos, preciso de saber...","pd_0_com_2extraD":"ExtraData","pd_0_com_2showmore":false,"pd_0_com_2visible":true,"pd_0_com_2audio":"","pd_0_com_2sprite":"","pd_isp_1":false,"pd_rect_1":[80,30],"pd_comSize_1":1,"pd_ID_1":1,"pd_pTag_1":"Narrador","pd_sprite_1":"Assets/VIDE/Data/Resources/Sprites/narrator.png","pd_expand_1":true,"pd_vars1":0,"pd_1_com_0iSet":1,"pd_1_com_0oAns":-1,"pd_1_com_0oAct":-1,"pd_1_com_0text":"Como te devo chamar?","pd_1_com_0extraD":"ExtraData","pd_1_com_0showmore":false,"pd_1_com_0visible":true,"pd_1_com_0audio":"","pd_1_com_0sprite":"","ac_rect_0":[-10,-190],"ac_ID_0":2,"ac_pause_0":false,"ac_goName_0":"VideUIManager","ac_nIndex_0":7,"ac_goto_0":-1,"ac_optsCount_0":15,"ac_opts_0_0":"[No method]","ac_opts_1_0":"GetAssigned","ac_opts_2_0":"AssignNew","ac_opts_3_0":"SaveState","ac_opts_4_0":"LoadState","ac_opts_5_0":"OnBeforeSerialize","ac_opts_6_0":"OnAfterDeserialize","ac_opts_7_0":"SetupAndStartDialogue","ac_opts_8_0":"SetupAndRestartDialogue","ac_opts_9_0":"InteractWithDialogue","ac_opts_10_0":"DisableContinueButton","ac_opts_11_0":"EnableContinueButton","ac_opts_12_0":"CallNext","ac_opts_13_0":"SetPlayerChoice","ac_opts_14_0":"DialogueEndActionHandler","ac_namesCount_0":15,"ac_names_0_0":"[No object]","ac_names_1_0":"Text (TMP)","ac_names_2_0":"Text (TMP)","ac_names_3_0":"Text (TMP)","ac_names_4_0":"Text (TMP)","ac_names_5_0":"DialogueText","ac_names_6_0":"NPCName","ac_names_7_0":"VideUIManager","ac_names_8_0":"AudioManager","ac_names_9_0":"SaveManager","ac_names_10_0":"IntroductionController","ac_names_11_0":"Text","ac_names_12_0":"TitleLb","ac_names_13_0":"NameRequest","ac_names_14_0":"Placeholder","ac_methCount_0":243,"ac_meth_key_0_0":"Text (TMP)0","ac_meth_val_0_0":"get_materialForRendering","ac_meth_key_0_1":"Text (TMP)1","ac_meth_val_0_1":"get_autoSizeTextContainer","ac_meth_key_0_2":"Text (TMP)2","ac_meth_val_0_2":"set_autoSizeTextContainer","ac_meth_key_0_3":"Text (TMP)3","ac_meth_val_0_3":"get_mesh","ac_meth_key_0_4":"Text (TMP)4","ac_meth_val_0_4":"get_canvasRenderer","ac_meth_key_0_5":"Text (TMP)5","ac_meth_val_0_5":"CalculateLayoutInputHorizontal","ac_meth_key_0_6":"Text (TMP)6","ac_meth_val_0_6":"CalculateLayoutInputVertical","ac_meth_key_0_7":"Text (TMP)7","ac_meth_val_0_7":"SetVerticesDirty","ac_meth_key_0_8":"Text (TMP)8","ac_meth_val_0_8":"SetLayoutDirty","ac_meth_key_0_9":"Text (TMP)9","ac_meth_val_0_9":"SetMaterialDirty","ac_meth_key_0_10":"Text (TMP)10","ac_meth_val_0_10":"SetAllDirty","ac_meth_key_0_11":"Text (TMP)11","ac_meth_val_0_11":"get_maskOffset","ac_meth_key_0_12":"Text (TMP)12","ac_meth_val_0_12":"RecalculateClipping","ac_meth_key_0_13":"Text (TMP)13","ac_meth_val_0_13":"UpdateMeshPadding","ac_meth_key_0_14":"Text (TMP)14","ac_meth_val_0_14":"GetTextInfo","ac_meth_key_0_15":"Text (TMP)15","ac_meth_val_0_15":"ClearMesh","ac_meth_key_0_16":"Text (TMP)16","ac_meth_val_0_16":"UpdateVertexData","ac_meth_key_0_17":"Text (TMP)17","ac_meth_val_0_17":"UpdateFontAsset","ac_meth_key_0_18":"Text (TMP)18","ac_meth_val_0_18":"ComputeMarginSize","ac_meth_key_0_19":"DialogueText0","ac_meth_val_0_19":"get_materialForRendering","ac_meth_key_0_20":"DialogueText1","ac_meth_val_0_20":"get_autoSizeTextContainer","ac_meth_key_0_21":"DialogueText2","ac_meth_val_0_21":"set_autoSizeTextContainer","ac_meth_key_0_22":"DialogueText3","ac_meth_val_0_22":"get_mesh","ac_meth_key_0_23":"DialogueText4","ac_meth_val_0_23":"get_canvasRenderer","ac_meth_key_0_24":"DialogueText5","ac_meth_val_0_24":"CalculateLayoutInputHorizontal","ac_meth_key_0_25":"DialogueText6","ac_meth_val_0_25":"CalculateLayoutInputVertical","ac_meth_key_0_26":"DialogueText7","ac_meth_val_0_26":"SetVerticesDirty","ac_meth_key_0_27":"DialogueText8","ac_meth_val_0_27":"SetLayoutDirty","ac_meth_key_0_28":"DialogueText9","ac_meth_val_0_28":"SetMaterialDirty","ac_meth_key_0_29":"DialogueText10","ac_meth_val_0_29":"SetAllDirty","ac_meth_key_0_30":"DialogueText11","ac_meth_val_0_30":"get_maskOffset","ac_meth_key_0_31":"DialogueText12","ac_meth_val_0_31":"RecalculateClipping","ac_meth_key_0_32":"DialogueText13","ac_meth_val_0_32":"UpdateMeshPadding","ac_meth_key_0_33":"DialogueText14","ac_meth_val_0_33":"GetTextInfo","ac_meth_key_0_34":"DialogueText15","ac_meth_val_0_34":"ClearMesh","ac_meth_key_0_35":"DialogueText16","ac_meth_val_0_35":"UpdateVertexData","ac_meth_key_0_36":"DialogueText17","ac_meth_val_0_36":"UpdateFontAsset","ac_meth_key_0_37":"DialogueText18","ac_meth_val_0_37":"ComputeMarginSize","ac_meth_key_0_38":"NPCName0","ac_meth_val_0_38":"get_materialForRendering","ac_meth_key_0_39":"NPCName1","ac_meth_val_0_39":"get_autoSizeTextContainer","ac_meth_key_0_40":"NPCName2","ac_meth_val_0_40":"set_autoSizeTextContainer","ac_meth_key_0_41":"NPCName3","ac_meth_val_0_41":"get_mesh","ac_meth_key_0_42":"NPCName4","ac_meth_val_0_42":"get_canvasRenderer","ac_meth_key_0_43":"NPCName5","ac_meth_val_0_43":"CalculateLayoutInputHorizontal","ac_meth_key_0_44":"NPCName6","ac_meth_val_0_44":"CalculateLayoutInputVertical","ac_meth_key_0_45":"NPCName7","ac_meth_val_0_45":"SetVerticesDirty","ac_meth_key_0_46":"NPCName8","ac_meth_val_0_46":"SetLayoutDirty","ac_meth_key_0_47":"NPCName9","ac_meth_val_0_47":"SetMaterialDirty","ac_meth_key_0_48":"NPCName10","ac_meth_val_0_48":"SetAllDirty","ac_meth_key_0_49":"NPCName11","ac_meth_val_0_49":"get_maskOffset","ac_meth_key_0_50":"NPCName12","ac_meth_val_0_50":"RecalculateClipping","ac_meth_key_0_51":"NPCName13","ac_meth_val_0_51":"UpdateMeshPadding","ac_meth_key_0_52":"NPCName14","ac_meth_val_0_52":"GetTextInfo","ac_meth_key_0_53":"NPCName15","ac_meth_val_0_53":"ClearMesh","ac_meth_key_0_54":"NPCName16","ac_meth_val_0_54":"UpdateVertexData","ac_meth_key_0_55":"NPCName17","ac_meth_val_0_55":"UpdateFontAsset","ac_meth_key_0_56":"NPCName18","ac_meth_val_0_56":"ComputeMarginSize","ac_meth_key_0_57":"VideUIManager0","ac_meth_val_0_57":"GetAssigned","ac_meth_key_0_58":"VideUIManager1","ac_meth_val_0_58":"AssignNew","ac_meth_key_0_59":"VideUIManager2","ac_meth_val_0_59":"SaveState","ac_meth_key_0_60":"VideUIManager3","ac_meth_val_0_60":"LoadState","ac_meth_key_0_61":"VideUIManager4","ac_meth_val_0_61":"OnBeforeSerialize","ac_meth_key_0_62":"VideUIManager5","ac_meth_val_0_62":"OnAfterDeserialize","ac_meth_key_0_63":"VideUIManager6","ac_meth_val_0_63":"SetupAndStartDialogue","ac_meth_key_0_64":"VideUIManager7","ac_meth_val_0_64":"SetupAndRestartDialogue","ac_meth_key_0_65":"VideUIManager8","ac_meth_val_0_65":"InteractWithDialogue","ac_meth_key_0_66":"VideUIManager9","ac_meth_val_0_66":"DisableContinueButton","ac_meth_key_0_67":"VideUIManager10","ac_meth_val_0_67":"EnableContinueButton","ac_meth_key_0_68":"VideUIManager11","ac_meth_val_0_68":"CallNext","ac_meth_key_0_69":"VideUIManager12","ac_meth_val_0_69":"SetPlayerChoice","ac_meth_key_0_70":"VideUIManager13","ac_meth_val_0_70":"DialogueEndActionHandler","ac_meth_key_0_71":"AudioManager0","ac_meth_val_0_71":"get_ListenerNumber","ac_meth_key_0_72":"AudioManager1","ac_meth_val_0_72":"StopAllAudios","ac_meth_key_0_73":"DialogueManager0","ac_meth_val_0_73":"OnDialogueClick","ac_meth_key_0_74":"DialogueManager1","ac_meth_val_0_74":"UpdateDialogueDataStructure","ac_meth_key_0_75":"DialogueManager2","ac_meth_val_0_75":"ResetText","ac_meth_key_0_76":"DialogueManager3","ac_meth_val_0_76":"StartTyping","ac_meth_key_0_77":"DialogueManager4","ac_meth_val_0_77":"NextLine","ac_meth_key_0_78":"DialogueManager5","ac_meth_val_0_78":"ActivateDialogue","ac_meth_key_0_79":"DialogueManager6","ac_meth_val_0_79":"DisableDialogue","ac_meth_key_0_80":"SaveManager0","ac_meth_val_0_80":"get_dialogueStructure","ac_meth_key_0_81":"SaveManager1","ac_meth_val_0_81":"GetSaveDir","ac_meth_key_0_82":"SaveManager2","ac_meth_val_0_82":"SaveState","ac_meth_key_0_83":"SaveManager3","ac_meth_val_0_83":"LoadState","ac_meth_key_0_84":"IntroductionController0","ac_meth_val_0_84":"SendIntroduction","ac_meth_key_0_85":"IntroductionController1","ac_meth_val_0_85":"IntroductionCompleted","ac_meth_key_0_86":"IntroductionController2","ac_meth_val_0_86":"OnNameEntered","ac_meth_key_0_87":"IntroductionController3","ac_meth_val_0_87":"DialogueCompleted","ac_meth_key_0_88":"IntroductionController4","ac_meth_val_0_88":"AskGender","ac_meth_key_0_89":"IntroductionController5","ac_meth_val_0_89":"GenderEntered","ac_meth_key_0_90":"IntroductionController6","ac_meth_val_0_90":"ChangeToScene2","ac_meth_key_0_91":"IntroductionController7","ac_meth_val_0_91":"ChangeToScene3","ac_meth_key_0_92":"IntroductionController8","ac_meth_val_0_92":"ChangeToGrandmasHouseScene1","ac_meth_key_0_93":"IntroductionController9","ac_meth_val_0_93":"OpenMainMenu","ac_meth_key_0_94":"IntroductionController10","ac_meth_val_0_94":"StartSpeechMachineGame","ac_meth_key_0_95":"IntroductionController11","ac_meth_val_0_95":"StartMainGame","ac_meth_key_0_96":"Text0","ac_meth_val_0_96":"get_materialForRendering","ac_meth_key_0_97":"Text1","ac_meth_val_0_97":"get_autoSizeTextContainer","ac_meth_key_0_98":"Text2","ac_meth_val_0_98":"set_autoSizeTextContainer","ac_meth_key_0_99":"Text3","ac_meth_val_0_99":"get_mesh","ac_meth_key_0_100":"Text4","ac_meth_val_0_100":"get_canvasRenderer","ac_meth_key_0_101":"Text5","ac_meth_val_0_101":"CalculateLayoutInputHorizontal","ac_meth_key_0_102":"Text6","ac_meth_val_0_102":"CalculateLayoutInputVertical","ac_meth_key_0_103":"Text7","ac_meth_val_0_103":"SetVerticesDirty","ac_meth_key_0_104":"Text8","ac_meth_val_0_104":"SetLayoutDirty","ac_meth_key_0_105":"Text9","ac_meth_val_0_105":"SetMaterialDirty","ac_meth_key_0_106":"Text10","ac_meth_val_0_106":"SetAllDirty","ac_meth_key_0_107":"Text11","ac_meth_val_0_107":"get_maskOffset","ac_meth_key_0_108":"Text12","ac_meth_val_0_108":"RecalculateClipping","ac_meth_key_0_109":"Text13","ac_meth_val_0_109":"UpdateMeshPadding","ac_meth_key_0_110":"Text14","ac_meth_val_0_110":"GetTextInfo","ac_meth_key_0_111":"Text15","ac_meth_val_0_111":"ClearMesh","ac_meth_key_0_112":"Text16","ac_meth_val_0_112":"UpdateVertexData","ac_meth_key_0_113":"Text17","ac_meth_val_0_113":"UpdateFontAsset","ac_meth_key_0_114":"Text18","ac_meth_val_0_114":"ComputeMarginSize","ac_meth_key_0_115":"TitleLb0","ac_meth_val_0_115":"get_materialForRendering","ac_meth_key_0_116":"TitleLb1","ac_meth_val_0_116":"get_autoSizeTextContainer","ac_meth_key_0_117":"TitleLb2","ac_meth_val_0_117":"set_autoSizeTextContainer","ac_meth_key_0_118":"TitleLb3","ac_meth_val_0_118":"get_mesh","ac_meth_key_0_119":"TitleLb4","ac_meth_val_0_119":"get_canvasRenderer","ac_meth_key_0_120":"TitleLb5","ac_meth_val_0_120":"CalculateLayoutInputHorizontal","ac_meth_key_0_121":"TitleLb6","ac_meth_val_0_121":"CalculateLayoutInputVertical","ac_meth_key_0_122":"TitleLb7","ac_meth_val_0_122":"SetVerticesDirty","ac_meth_key_0_123":"TitleLb8","ac_meth_val_0_123":"SetLayoutDirty","ac_meth_key_0_124":"TitleLb9","ac_meth_val_0_124":"SetMaterialDirty","ac_meth_key_0_125":"TitleLb10","ac_meth_val_0_125":"SetAllDirty","ac_meth_key_0_126":"TitleLb11","ac_meth_val_0_126":"get_maskOffset","ac_meth_key_0_127":"TitleLb12","ac_meth_val_0_127":"RecalculateClipping","ac_meth_key_0_128":"TitleLb13","ac_meth_val_0_128":"UpdateMeshPadding","ac_meth_key_0_129":"TitleLb14","ac_meth_val_0_129":"GetTextInfo","ac_meth_key_0_130":"TitleLb15","ac_meth_val_0_130":"ClearMesh","ac_meth_key_0_131":"TitleLb16","ac_meth_val_0_131":"UpdateVertexData","ac_meth_key_0_132":"TitleLb17","ac_meth_val_0_132":"UpdateFontAsset","ac_meth_key_0_133":"TitleLb18","ac_meth_val_0_133":"ComputeMarginSize","ac_meth_key_0_134":"NameRequest0","ac_meth_val_0_134":"get_shouldHideMobileInput","ac_meth_key_0_135":"NameRequest1","ac_meth_val_0_135":"set_shouldHideMobileInput","ac_meth_key_0_136":"NameRequest2","ac_meth_val_0_136":"get_shouldHideSoftKeyboard","ac_meth_key_0_137":"NameRequest3","ac_meth_val_0_137":"set_shouldHideSoftKeyboard","ac_meth_key_0_138":"NameRequest4","ac_meth_val_0_138":"get_text","ac_meth_key_0_139":"NameRequest5","ac_meth_val_0_139":"set_text","ac_meth_key_0_140":"NameRequest6","ac_meth_val_0_140":"SetTextWithoutNotify","ac_meth_key_0_141":"NameRequest7","ac_meth_val_0_141":"get_isFocused","ac_meth_key_0_142":"NameRequest8","ac_meth_val_0_142":"get_caretBlinkRate","ac_meth_key_0_143":"NameRequest9","ac_meth_val_0_143":"set_caretBlinkRate","ac_meth_key_0_144":"NameRequest10","ac_meth_val_0_144":"get_caretWidth","ac_meth_key_0_145":"NameRequest11","ac_meth_val_0_145":"set_caretWidth","ac_meth_key_0_146":"NameRequest12","ac_meth_val_0_146":"get_textViewport","ac_meth_key_0_147":"NameRequest13","ac_meth_val_0_147":"get_textComponent","ac_meth_key_0_148":"NameRequest14","ac_meth_val_0_148":"get_placeholder","ac_meth_key_0_149":"NameRequest15","ac_meth_val_0_149":"get_verticalScrollbar","ac_meth_key_0_150":"NameRequest16","ac_meth_val_0_150":"get_scrollSensitivity","ac_meth_key_0_151":"NameRequest17","ac_meth_val_0_151":"set_scrollSensitivity","ac_meth_key_0_152":"NameRequest18","ac_meth_val_0_152":"get_caretColor","ac_meth_key_0_153":"NameRequest19","ac_meth_val_0_153":"get_customCaretColor","ac_meth_key_0_154":"NameRequest20","ac_meth_val_0_154":"set_customCaretColor","ac_meth_key_0_155":"NameRequest21","ac_meth_val_0_155":"get_selectionColor","ac_meth_key_0_156":"NameRequest22","ac_meth_val_0_156":"get_onEndEdit","ac_meth_key_0_157":"NameRequest23","ac_meth_val_0_157":"get_onSubmit","ac_meth_key_0_158":"NameRequest24","ac_meth_val_0_158":"get_onSelect","ac_meth_key_0_159":"NameRequest25","ac_meth_val_0_159":"get_onDeselect","ac_meth_key_0_160":"NameRequest26","ac_meth_val_0_160":"get_onTextSelection","ac_meth_key_0_161":"NameRequest27","ac_meth_val_0_161":"get_onEndTextSelection","ac_meth_key_0_162":"NameRequest28","ac_meth_val_0_162":"get_onValueChanged","ac_meth_key_0_163":"NameRequest29","ac_meth_val_0_163":"get_onTouchScreenKeyboardStatusChanged","ac_meth_key_0_164":"NameRequest30","ac_meth_val_0_164":"get_onValidateInput","ac_meth_key_0_165":"NameRequest31","ac_meth_val_0_165":"get_characterLimit","ac_meth_key_0_166":"NameRequest32","ac_meth_val_0_166":"set_characterLimit","ac_meth_key_0_167":"NameRequest33","ac_meth_val_0_167":"get_pointSize","ac_meth_key_0_168":"NameRequest34","ac_meth_val_0_168":"set_pointSize","ac_meth_key_0_169":"NameRequest35","ac_meth_val_0_169":"get_fontAsset","ac_meth_key_0_170":"NameRequest36","ac_meth_val_0_170":"get_onFocusSelectAll","ac_meth_key_0_171":"NameRequest37","ac_meth_val_0_171":"set_onFocusSelectAll","ac_meth_key_0_172":"NameRequest38","ac_meth_val_0_172":"get_resetOnDeActivation","ac_meth_key_0_173":"NameRequest39","ac_meth_val_0_173":"set_resetOnDeActivation","ac_meth_key_0_174":"NameRequest40","ac_meth_val_0_174":"get_restoreOriginalTextOnEscape","ac_meth_key_0_175":"NameRequest41","ac_meth_val_0_175":"set_restoreOriginalTextOnEscape","ac_meth_key_0_176":"NameRequest42","ac_meth_val_0_176":"get_isRichTextEditingAllowed","ac_meth_key_0_177":"NameRequest43","ac_meth_val_0_177":"set_isRichTextEditingAllowed","ac_meth_key_0_178":"NameRequest44","ac_meth_val_0_178":"get_contentType","ac_meth_key_0_179":"NameRequest45","ac_meth_val_0_179":"get_lineType","ac_meth_key_0_180":"NameRequest46","ac_meth_val_0_180":"get_lineLimit","ac_meth_key_0_181":"NameRequest47","ac_meth_val_0_181":"set_lineLimit","ac_meth_key_0_182":"NameRequest48","ac_meth_val_0_182":"get_inputType","ac_meth_key_0_183":"NameRequest49","ac_meth_val_0_183":"get_keyboardType","ac_meth_key_0_184":"NameRequest50","ac_meth_val_0_184":"get_characterValidation","ac_meth_key_0_185":"NameRequest51","ac_meth_val_0_185":"get_inputValidator","ac_meth_key_0_186":"NameRequest52","ac_meth_val_0_186":"get_readOnly","ac_meth_key_0_187":"NameRequest53","ac_meth_val_0_187":"set_readOnly","ac_meth_key_0_188":"NameRequest54","ac_meth_val_0_188":"get_richText","ac_meth_key_0_189":"NameRequest55","ac_meth_val_0_189":"set_richText","ac_meth_key_0_190":"NameRequest56","ac_meth_val_0_190":"get_multiLine","ac_meth_key_0_191":"NameRequest57","ac_meth_val_0_191":"get_asteriskChar","ac_meth_key_0_192":"NameRequest58","ac_meth_val_0_192":"get_wasCanceled","ac_meth_key_0_193":"NameRequest59","ac_meth_val_0_193":"get_caretPosition","ac_meth_key_0_194":"NameRequest60","ac_meth_val_0_194":"set_caretPosition","ac_meth_key_0_195":"NameRequest61","ac_meth_val_0_195":"get_selectionAnchorPosition","ac_meth_key_0_196":"NameRequest62","ac_meth_val_0_196":"set_selectionAnchorPosition","ac_meth_key_0_197":"NameRequest63","ac_meth_val_0_197":"get_selectionFocusPosition","ac_meth_key_0_198":"NameRequest64","ac_meth_val_0_198":"set_selectionFocusPosition","ac_meth_key_0_199":"NameRequest65","ac_meth_val_0_199":"get_stringPosition","ac_meth_key_0_200":"NameRequest66","ac_meth_val_0_200":"set_stringPosition","ac_meth_key_0_201":"NameRequest67","ac_meth_val_0_201":"get_selectionStringAnchorPosition","ac_meth_key_0_202":"NameRequest68","ac_meth_val_0_202":"set_selectionStringAnchorPosition","ac_meth_key_0_203":"NameRequest69","ac_meth_val_0_203":"get_selectionStringFocusPosition","ac_meth_key_0_204":"NameRequest70","ac_meth_val_0_204":"set_selectionStringFocusPosition","ac_meth_key_0_205":"NameRequest71","ac_meth_val_0_205":"MoveTextEnd","ac_meth_key_0_206":"NameRequest72","ac_meth_val_0_206":"MoveTextStart","ac_meth_key_0_207":"NameRequest73","ac_meth_val_0_207":"ForceLabelUpdate","ac_meth_key_0_208":"NameRequest74","ac_meth_val_0_208":"LayoutComplete","ac_meth_key_0_209":"NameRequest75","ac_meth_val_0_209":"GraphicUpdateComplete","ac_meth_key_0_210":"NameRequest76","ac_meth_val_0_210":"ActivateInputField","ac_meth_key_0_211":"NameRequest77","ac_meth_val_0_211":"OnControlClick","ac_meth_key_0_212":"NameRequest78","ac_meth_val_0_212":"ReleaseSelection","ac_meth_key_0_213":"NameRequest79","ac_meth_val_0_213":"DeactivateInputField","ac_meth_key_0_214":"NameRequest80","ac_meth_val_0_214":"CalculateLayoutInputHorizontal","ac_meth_key_0_215":"NameRequest81","ac_meth_val_0_215":"CalculateLayoutInputVertical","ac_meth_key_0_216":"NameRequest82","ac_meth_val_0_216":"get_minWidth","ac_meth_key_0_217":"NameRequest83","ac_meth_val_0_217":"get_preferredWidth","ac_meth_key_0_218":"NameRequest84","ac_meth_val_0_218":"get_flexibleWidth","ac_meth_key_0_219":"NameRequest85","ac_meth_val_0_219":"get_minHeight","ac_meth_key_0_220":"NameRequest86","ac_meth_val_0_220":"get_preferredHeight","ac_meth_key_0_221":"NameRequest87","ac_meth_val_0_221":"get_flexibleHeight","ac_meth_key_0_222":"NameRequest88","ac_meth_val_0_222":"get_layoutPriority","ac_meth_key_0_223":"NameRequest89","ac_meth_val_0_223":"SetGlobalPointSize","ac_meth_key_0_224":"Placeholder0","ac_meth_val_0_224":"get_materialForRendering","ac_meth_key_0_225":"Placeholder1","ac_meth_val_0_225":"get_autoSizeTextContainer","ac_meth_key_0_226":"Placeholder2","ac_meth_val_0_226":"set_autoSizeTextContainer","ac_meth_key_0_227":"Placeholder3","ac_meth_val_0_227":"get_mesh","ac_meth_key_0_228":"Placeholder4","ac_meth_val_0_228":"get_canvasRenderer","ac_meth_key_0_229":"Placeholder5","ac_meth_val_0_229":"CalculateLayoutInputHorizontal","ac_meth_key_0_230":"Placeholder6","ac_meth_val_0_230":"CalculateLayoutInputVertical","ac_meth_key_0_231":"Placeholder7","ac_meth_val_0_231":"SetVerticesDirty","ac_meth_key_0_232":"Placeholder8","ac_meth_val_0_232":"SetLayoutDirty","ac_meth_key_0_233":"Placeholder9","ac_meth_val_0_233":"SetMaterialDirty","ac_meth_key_0_234":"Placeholder10","ac_meth_val_0_234":"SetAllDirty","ac_meth_key_0_235":"Placeholder11","ac_meth_val_0_235":"get_maskOffset","ac_meth_key_0_236":"Placeholder12","ac_meth_val_0_236":"RecalculateClipping","ac_meth_key_0_237":"Placeholder13","ac_meth_val_0_237":"UpdateMeshPadding","ac_meth_key_0_238":"Placeholder14","ac_meth_val_0_238":"GetTextInfo","ac_meth_key_0_239":"Placeholder15","ac_meth_val_0_239":"ClearMesh","ac_meth_key_0_240":"Placeholder16","ac_meth_val_0_240":"UpdateVertexData","ac_meth_key_0_241":"Placeholder17","ac_meth_val_0_241":"UpdateFontAsset","ac_meth_key_0_242":"Placeholder18","ac_meth_val_0_242":"ComputeMarginSize","ac_meth_0":"DisableContinueButton","ac_paramT_0":0,"ac_methIndex_0":10,"ac_pString_0":null,"ac_pBool_0":false,"ac_pInt_0":0,"ac_pFloat_0":0,"ac_oSet_0":-1,"ac_oAct_0":1,"ac_ovrStartNode_0":-1,"ac_renameDialogue_0":"","ac_more_0":false,"ac_rect_1":[230,-200],"ac_ID_1":3,"ac_pause_1":false,"ac_goName_1":"IntroductionController","ac_nIndex_1":10,"ac_goto_1":-1,"ac_optsCount_1":13,"ac_opts_0_1":"[No method]","ac_opts_1_1":"SendIntroduction","ac_opts_2_1":"IntroductionCompleted","ac_opts_3_1":"OnNameEntered","ac_opts_4_1":"DialogueCompleted","ac_opts_5_1":"AskGender","ac_opts_6_1":"GenderEntered","ac_opts_7_1":"ChangeToScene2","ac_opts_8_1":"ChangeToScene3","ac_opts_9_1":"ChangeToGrandmasHouseScene1","ac_opts_10_1":"OpenMainMenu","ac_opts_11_1":"StartSpeechMachineGame","ac_opts_12_1":"StartMainGame","ac_namesCount_1":15,"ac_names_0_1":"[No object]","ac_names_1_1":"Text (TMP)","ac_names_2_1":"Text (TMP)","ac_names_3_1":"Text (TMP)","ac_names_4_1":"Text (TMP)","ac_names_5_1":"DialogueText","ac_names_6_1":"NPCName","ac_names_7_1":"VideUIManager","ac_names_8_1":"AudioManager","ac_names_9_1":"SaveManager","ac_names_10_1":"IntroductionController","ac_names_11_1":"Text","ac_names_12_1":"TitleLb","ac_names_13_1":"NameRequest","ac_names_14_1":"Placeholder","ac_methCount_1":236,"ac_meth_key_1_0":"Text (TMP)0","ac_meth_val_1_0":"get_materialForRendering","ac_meth_key_1_1":"Text (TMP)1","ac_meth_val_1_1":"get_autoSizeTextContainer","ac_meth_key_1_2":"Text (TMP)2","ac_meth_val_1_2":"set_autoSizeTextContainer","ac_meth_key_1_3":"Text (TMP)3","ac_meth_val_1_3":"get_mesh","ac_meth_key_1_4":"Text (TMP)4","ac_meth_val_1_4":"get_canvasRenderer","ac_meth_key_1_5":"Text (TMP)5","ac_meth_val_1_5":"CalculateLayoutInputHorizontal","ac_meth_key_1_6":"Text (TMP)6","ac_meth_val_1_6":"CalculateLayoutInputVertical","ac_meth_key_1_7":"Text (TMP)7","ac_meth_val_1_7":"SetVerticesDirty","ac_meth_key_1_8":"Text (TMP)8","ac_meth_val_1_8":"SetLayoutDirty","ac_meth_key_1_9":"Text (TMP)9","ac_meth_val_1_9":"SetMaterialDirty","ac_meth_key_1_10":"Text (TMP)10","ac_meth_val_1_10":"SetAllDirty","ac_meth_key_1_11":"Text (TMP)11","ac_meth_val_1_11":"get_maskOffset","ac_meth_key_1_12":"Text (TMP)12","ac_meth_val_1_12":"RecalculateClipping","ac_meth_key_1_13":"Text (TMP)13","ac_meth_val_1_13":"UpdateMeshPadding","ac_meth_key_1_14":"Text (TMP)14","ac_meth_val_1_14":"GetTextInfo","ac_meth_key_1_15":"Text (TMP)15","ac_meth_val_1_15":"ClearMesh","ac_meth_key_1_16":"Text (TMP)16","ac_meth_val_1_16":"UpdateVertexData","ac_meth_key_1_17":"Text (TMP)17","ac_meth_val_1_17":"UpdateFontAsset","ac_meth_key_1_18":"Text (TMP)18","ac_meth_val_1_18":"ComputeMarginSize","ac_meth_key_1_19":"DialogueText0","ac_meth_val_1_19":"get_materialForRendering","ac_meth_key_1_20":"DialogueText1","ac_meth_val_1_20":"get_autoSizeTextContainer","ac_meth_key_1_21":"DialogueText2","ac_meth_val_1_21":"set_autoSizeTextContainer","ac_meth_key_1_22":"DialogueText3","ac_meth_val_1_22":"get_mesh","ac_meth_key_1_23":"DialogueText4","ac_meth_val_1_23":"get_canvasRenderer","ac_meth_key_1_24":"DialogueText5","ac_meth_val_1_24":"CalculateLayoutInputHorizontal","ac_meth_key_1_25":"DialogueText6","ac_meth_val_1_25":"CalculateLayoutInputVertical","ac_meth_key_1_26":"DialogueText7","ac_meth_val_1_26":"SetVerticesDirty","ac_meth_key_1_27":"DialogueText8","ac_meth_val_1_27":"SetLayoutDirty","ac_meth_key_1_28":"DialogueText9","ac_meth_val_1_28":"SetMaterialDirty","ac_meth_key_1_29":"DialogueText10","ac_meth_val_1_29":"SetAllDirty","ac_meth_key_1_30":"DialogueText11","ac_meth_val_1_30":"get_maskOffset","ac_meth_key_1_31":"DialogueText12","ac_meth_val_1_31":"RecalculateClipping","ac_meth_key_1_32":"DialogueText13","ac_meth_val_1_32":"UpdateMeshPadding","ac_meth_key_1_33":"DialogueText14","ac_meth_val_1_33":"GetTextInfo","ac_meth_key_1_34":"DialogueText15","ac_meth_val_1_34":"ClearMesh","ac_meth_key_1_35":"DialogueText16","ac_meth_val_1_35":"UpdateVertexData","ac_meth_key_1_36":"DialogueText17","ac_meth_val_1_36":"UpdateFontAsset","ac_meth_key_1_37":"DialogueText18","ac_meth_val_1_37":"ComputeMarginSize","ac_meth_key_1_38":"NPCName0","ac_meth_val_1_38":"get_materialForRendering","ac_meth_key_1_39":"NPCName1","ac_meth_val_1_39":"get_autoSizeTextContainer","ac_meth_key_1_40":"NPCName2","ac_meth_val_1_40":"set_autoSizeTextContainer","ac_meth_key_1_41":"NPCName3","ac_meth_val_1_41":"get_mesh","ac_meth_key_1_42":"NPCName4","ac_meth_val_1_42":"get_canvasRenderer","ac_meth_key_1_43":"NPCName5","ac_meth_val_1_43":"CalculateLayoutInputHorizontal","ac_meth_key_1_44":"NPCName6","ac_meth_val_1_44":"CalculateLayoutInputVertical","ac_meth_key_1_45":"NPCName7","ac_meth_val_1_45":"SetVerticesDirty","ac_meth_key_1_46":"NPCName8","ac_meth_val_1_46":"SetLayoutDirty","ac_meth_key_1_47":"NPCName9","ac_meth_val_1_47":"SetMaterialDirty","ac_meth_key_1_48":"NPCName10","ac_meth_val_1_48":"SetAllDirty","ac_meth_key_1_49":"NPCName11","ac_meth_val_1_49":"get_maskOffset","ac_meth_key_1_50":"NPCName12","ac_meth_val_1_50":"RecalculateClipping","ac_meth_key_1_51":"NPCName13","ac_meth_val_1_51":"UpdateMeshPadding","ac_meth_key_1_52":"NPCName14","ac_meth_val_1_52":"GetTextInfo","ac_meth_key_1_53":"NPCName15","ac_meth_val_1_53":"ClearMesh","ac_meth_key_1_54":"NPCName16","ac_meth_val_1_54":"UpdateVertexData","ac_meth_key_1_55":"NPCName17","ac_meth_val_1_55":"UpdateFontAsset","ac_meth_key_1_56":"NPCName18","ac_meth_val_1_56":"ComputeMarginSize","ac_meth_key_1_57":"VideUIManager0","ac_meth_val_1_57":"GetAssigned","ac_meth_key_1_58":"VideUIManager1","ac_meth_val_1_58":"AssignNew","ac_meth_key_1_59":"VideUIManager2","ac_meth_val_1_59":"SaveState","ac_meth_key_1_60":"VideUIManager3","ac_meth_val_1_60":"LoadState","ac_meth_key_1_61":"VideUIManager4","ac_meth_val_1_61":"OnBeforeSerialize","ac_meth_key_1_62":"VideUIManager5","ac_meth_val_1_62":"OnAfterDeserialize","ac_meth_key_1_63":"VideUIManager6","ac_meth_val_1_63":"SetupAndStartDialogue","ac_meth_key_1_64":"VideUIManager7","ac_meth_val_1_64":"SetupAndRestartDialogue","ac_meth_key_1_65":"VideUIManager8","ac_meth_val_1_65":"InteractWithDialogue","ac_meth_key_1_66":"VideUIManager9","ac_meth_val_1_66":"DisableContinueButton","ac_meth_key_1_67":"VideUIManager10","ac_meth_val_1_67":"EnableContinueButton","ac_meth_key_1_68":"VideUIManager11","ac_meth_val_1_68":"CallNext","ac_meth_key_1_69":"VideUIManager12","ac_meth_val_1_69":"SetPlayerChoice","ac_meth_key_1_70":"VideUIManager13","ac_meth_val_1_70":"DialogueEndActionHandler","ac_meth_key_1_71":"AudioManager0","ac_meth_val_1_71":"get_ListenerNumber","ac_meth_key_1_72":"AudioManager1","ac_meth_val_1_72":"StopAllAudios","ac_meth_key_1_73":"SaveManager0","ac_meth_val_1_73":"get_dialogueStructure","ac_meth_key_1_74":"SaveManager1","ac_meth_val_1_74":"GetSaveDir","ac_meth_key_1_75":"SaveManager2","ac_meth_val_1_75":"SaveState","ac_meth_key_1_76":"SaveManager3","ac_meth_val_1_76":"LoadState","ac_meth_key_1_77":"IntroductionController0","ac_meth_val_1_77":"SendIntroduction","ac_meth_key_1_78":"IntroductionController1","ac_meth_val_1_78":"IntroductionCompleted","ac_meth_key_1_79":"IntroductionController2","ac_meth_val_1_79":"OnNameEntered","ac_meth_key_1_80":"IntroductionController3","ac_meth_val_1_80":"DialogueCompleted","ac_meth_key_1_81":"IntroductionController4","ac_meth_val_1_81":"AskGender","ac_meth_key_1_82":"IntroductionController5","ac_meth_val_1_82":"GenderEntered","ac_meth_key_1_83":"IntroductionController6","ac_meth_val_1_83":"ChangeToScene2","ac_meth_key_1_84":"IntroductionController7","ac_meth_val_1_84":"ChangeToScene3","ac_meth_key_1_85":"IntroductionController8","ac_meth_val_1_85":"ChangeToGrandmasHouseScene1","ac_meth_key_1_86":"IntroductionController9","ac_meth_val_1_86":"OpenMainMenu","ac_meth_key_1_87":"IntroductionController10","ac_meth_val_1_87":"StartSpeechMachineGame","ac_meth_key_1_88":"IntroductionController11","ac_meth_val_1_88":"StartMainGame","ac_meth_key_1_89":"Text0","ac_meth_val_1_89":"get_materialForRendering","ac_meth_key_1_90":"Text1","ac_meth_val_1_90":"get_autoSizeTextContainer","ac_meth_key_1_91":"Text2","ac_meth_val_1_91":"set_autoSizeTextContainer","ac_meth_key_1_92":"Text3","ac_meth_val_1_92":"get_mesh","ac_meth_key_1_93":"Text4","ac_meth_val_1_93":"get_canvasRenderer","ac_meth_key_1_94":"Text5","ac_meth_val_1_94":"CalculateLayoutInputHorizontal","ac_meth_key_1_95":"Text6","ac_meth_val_1_95":"CalculateLayoutInputVertical","ac_meth_key_1_96":"Text7","ac_meth_val_1_96":"SetVerticesDirty","ac_meth_key_1_97":"Text8","ac_meth_val_1_97":"SetLayoutDirty","ac_meth_key_1_98":"Text9","ac_meth_val_1_98":"SetMaterialDirty","ac_meth_key_1_99":"Text10","ac_meth_val_1_99":"SetAllDirty","ac_meth_key_1_100":"Text11","ac_meth_val_1_100":"get_maskOffset","ac_meth_key_1_101":"Text12","ac_meth_val_1_101":"RecalculateClipping","ac_meth_key_1_102":"Text13","ac_meth_val_1_102":"UpdateMeshPadding","ac_meth_key_1_103":"Text14","ac_meth_val_1_103":"GetTextInfo","ac_meth_key_1_104":"Text15","ac_meth_val_1_104":"ClearMesh","ac_meth_key_1_105":"Text16","ac_meth_val_1_105":"UpdateVertexData","ac_meth_key_1_106":"Text17","ac_meth_val_1_106":"UpdateFontAsset","ac_meth_key_1_107":"Text18","ac_meth_val_1_107":"ComputeMarginSize","ac_meth_key_1_108":"TitleLb0","ac_meth_val_1_108":"get_materialForRendering","ac_meth_key_1_109":"TitleLb1","ac_meth_val_1_109":"get_autoSizeTextContainer","ac_meth_key_1_110":"TitleLb2","ac_meth_val_1_110":"set_autoSizeTextContainer","ac_meth_key_1_111":"TitleLb3","ac_meth_val_1_111":"get_mesh","ac_meth_key_1_112":"TitleLb4","ac_meth_val_1_112":"get_canvasRenderer","ac_meth_key_1_113":"TitleLb5","ac_meth_val_1_113":"CalculateLayoutInputHorizontal","ac_meth_key_1_114":"TitleLb6","ac_meth_val_1_114":"CalculateLayoutInputVertical","ac_meth_key_1_115":"TitleLb7","ac_meth_val_1_115":"SetVerticesDirty","ac_meth_key_1_116":"TitleLb8","ac_meth_val_1_116":"SetLayoutDirty","ac_meth_key_1_117":"TitleLb9","ac_meth_val_1_117":"SetMaterialDirty","ac_meth_key_1_118":"TitleLb10","ac_meth_val_1_118":"SetAllDirty","ac_meth_key_1_119":"TitleLb11","ac_meth_val_1_119":"get_maskOffset","ac_meth_key_1_120":"TitleLb12","ac_meth_val_1_120":"RecalculateClipping","ac_meth_key_1_121":"TitleLb13","ac_meth_val_1_121":"UpdateMeshPadding","ac_meth_key_1_122":"TitleLb14","ac_meth_val_1_122":"GetTextInfo","ac_meth_key_1_123":"TitleLb15","ac_meth_val_1_123":"ClearMesh","ac_meth_key_1_124":"TitleLb16","ac_meth_val_1_124":"UpdateVertexData","ac_meth_key_1_125":"TitleLb17","ac_meth_val_1_125":"UpdateFontAsset","ac_meth_key_1_126":"TitleLb18","ac_meth_val_1_126":"ComputeMarginSize","ac_meth_key_1_127":"NameRequest0","ac_meth_val_1_127":"get_shouldHideMobileInput","ac_meth_key_1_128":"NameRequest1","ac_meth_val_1_128":"set_shouldHideMobileInput","ac_meth_key_1_129":"NameRequest2","ac_meth_val_1_129":"get_shouldHideSoftKeyboard","ac_meth_key_1_130":"NameRequest3","ac_meth_val_1_130":"set_shouldHideSoftKeyboard","ac_meth_key_1_131":"NameRequest4","ac_meth_val_1_131":"get_text","ac_meth_key_1_132":"NameRequest5","ac_meth_val_1_132":"set_text","ac_meth_key_1_133":"NameRequest6","ac_meth_val_1_133":"SetTextWithoutNotify","ac_meth_key_1_134":"NameRequest7","ac_meth_val_1_134":"get_isFocused","ac_meth_key_1_135":"NameRequest8","ac_meth_val_1_135":"get_caretBlinkRate","ac_meth_key_1_136":"NameRequest9","ac_meth_val_1_136":"set_caretBlinkRate","ac_meth_key_1_137":"NameRequest10","ac_meth_val_1_137":"get_caretWidth","ac_meth_key_1_138":"NameRequest11","ac_meth_val_1_138":"set_caretWidth","ac_meth_key_1_139":"NameRequest12","ac_meth_val_1_139":"get_textViewport","ac_meth_key_1_140":"NameRequest13","ac_meth_val_1_140":"get_textComponent","ac_meth_key_1_141":"NameRequest14","ac_meth_val_1_141":"get_placeholder","ac_meth_key_1_142":"NameRequest15","ac_meth_val_1_142":"get_verticalScrollbar","ac_meth_key_1_143":"NameRequest16","ac_meth_val_1_143":"get_scrollSensitivity","ac_meth_key_1_144":"NameRequest17","ac_meth_val_1_144":"set_scrollSensitivity","ac_meth_key_1_145":"NameRequest18","ac_meth_val_1_145":"get_caretColor","ac_meth_key_1_146":"NameRequest19","ac_meth_val_1_146":"get_customCaretColor","ac_meth_key_1_147":"NameRequest20","ac_meth_val_1_147":"set_customCaretColor","ac_meth_key_1_148":"NameRequest21","ac_meth_val_1_148":"get_selectionColor","ac_meth_key_1_149":"NameRequest22","ac_meth_val_1_149":"get_onEndEdit","ac_meth_key_1_150":"NameRequest23","ac_meth_val_1_150":"get_onSubmit","ac_meth_key_1_151":"NameRequest24","ac_meth_val_1_151":"get_onSelect","ac_meth_key_1_152":"NameRequest25","ac_meth_val_1_152":"get_onDeselect","ac_meth_key_1_153":"NameRequest26","ac_meth_val_1_153":"get_onTextSelection","ac_meth_key_1_154":"NameRequest27","ac_meth_val_1_154":"get_onEndTextSelection","ac_meth_key_1_155":"NameRequest28","ac_meth_val_1_155":"get_onValueChanged","ac_meth_key_1_156":"NameRequest29","ac_meth_val_1_156":"get_onTouchScreenKeyboardStatusChanged","ac_meth_key_1_157":"NameRequest30","ac_meth_val_1_157":"get_onValidateInput","ac_meth_key_1_158":"NameRequest31","ac_meth_val_1_158":"get_characterLimit","ac_meth_key_1_159":"NameRequest32","ac_meth_val_1_159":"set_characterLimit","ac_meth_key_1_160":"NameRequest33","ac_meth_val_1_160":"get_pointSize","ac_meth_key_1_161":"NameRequest34","ac_meth_val_1_161":"set_pointSize","ac_meth_key_1_162":"NameRequest35","ac_meth_val_1_162":"get_fontAsset","ac_meth_key_1_163":"NameRequest36","ac_meth_val_1_163":"get_onFocusSelectAll","ac_meth_key_1_164":"NameRequest37","ac_meth_val_1_164":"set_onFocusSelectAll","ac_meth_key_1_165":"NameRequest38","ac_meth_val_1_165":"get_resetOnDeActivation","ac_meth_key_1_166":"NameRequest39","ac_meth_val_1_166":"set_resetOnDeActivation","ac_meth_key_1_167":"NameRequest40","ac_meth_val_1_167":"get_restoreOriginalTextOnEscape","ac_meth_key_1_168":"NameRequest41","ac_meth_val_1_168":"set_restoreOriginalTextOnEscape","ac_meth_key_1_169":"NameRequest42","ac_meth_val_1_169":"get_isRichTextEditingAllowed","ac_meth_key_1_170":"NameRequest43","ac_meth_val_1_170":"set_isRichTextEditingAllowed","ac_meth_key_1_171":"NameRequest44","ac_meth_val_1_171":"get_contentType","ac_meth_key_1_172":"NameRequest45","ac_meth_val_1_172":"get_lineType","ac_meth_key_1_173":"NameRequest46","ac_meth_val_1_173":"get_lineLimit","ac_meth_key_1_174":"NameRequest47","ac_meth_val_1_174":"set_lineLimit","ac_meth_key_1_175":"NameRequest48","ac_meth_val_1_175":"get_inputType","ac_meth_key_1_176":"NameRequest49","ac_meth_val_1_176":"get_keyboardType","ac_meth_key_1_177":"NameRequest50","ac_meth_val_1_177":"get_characterValidation","ac_meth_key_1_178":"NameRequest51","ac_meth_val_1_178":"get_inputValidator","ac_meth_key_1_179":"NameRequest52","ac_meth_val_1_179":"get_readOnly","ac_meth_key_1_180":"NameRequest53","ac_meth_val_1_180":"set_readOnly","ac_meth_key_1_181":"NameRequest54","ac_meth_val_1_181":"get_richText","ac_meth_key_1_182":"NameRequest55","ac_meth_val_1_182":"set_richText","ac_meth_key_1_183":"NameRequest56","ac_meth_val_1_183":"get_multiLine","ac_meth_key_1_184":"NameRequest57","ac_meth_val_1_184":"get_asteriskChar","ac_meth_key_1_185":"NameRequest58","ac_meth_val_1_185":"get_wasCanceled","ac_meth_key_1_186":"NameRequest59","ac_meth_val_1_186":"get_caretPosition","ac_meth_key_1_187":"NameRequest60","ac_meth_val_1_187":"set_caretPosition","ac_meth_key_1_188":"NameRequest61","ac_meth_val_1_188":"get_selectionAnchorPosition","ac_meth_key_1_189":"NameRequest62","ac_meth_val_1_189":"set_selectionAnchorPosition","ac_meth_key_1_190":"NameRequest63","ac_meth_val_1_190":"get_selectionFocusPosition","ac_meth_key_1_191":"NameRequest64","ac_meth_val_1_191":"set_selectionFocusPosition","ac_meth_key_1_192":"NameRequest65","ac_meth_val_1_192":"get_stringPosition","ac_meth_key_1_193":"NameRequest66","ac_meth_val_1_193":"set_stringPosition","ac_meth_key_1_194":"NameRequest67","ac_meth_val_1_194":"get_selectionStringAnchorPosition","ac_meth_key_1_195":"NameRequest68","ac_meth_val_1_195":"set_selectionStringAnchorPosition","ac_meth_key_1_196":"NameRequest69","ac_meth_val_1_196":"get_selectionStringFocusPosition","ac_meth_key_1_197":"NameRequest70","ac_meth_val_1_197":"set_selectionStringFocusPosition","ac_meth_key_1_198":"NameRequest71","ac_meth_val_1_198":"MoveTextEnd","ac_meth_key_1_199":"NameRequest72","ac_meth_val_1_199":"MoveTextStart","ac_meth_key_1_200":"NameRequest73","ac_meth_val_1_200":"ForceLabelUpdate","ac_meth_key_1_201":"NameRequest74","ac_meth_val_1_201":"LayoutComplete","ac_meth_key_1_202":"NameRequest75","ac_meth_val_1_202":"GraphicUpdateComplete","ac_meth_key_1_203":"NameRequest76","ac_meth_val_1_203":"ActivateInputField","ac_meth_key_1_204":"NameRequest77","ac_meth_val_1_204":"OnControlClick","ac_meth_key_1_205":"NameRequest78","ac_meth_val_1_205":"ReleaseSelection","ac_meth_key_1_206":"NameRequest79","ac_meth_val_1_206":"DeactivateInputField","ac_meth_key_1_207":"NameRequest80","ac_meth_val_1_207":"CalculateLayoutInputHorizontal","ac_meth_key_1_208":"NameRequest81","ac_meth_val_1_208":"CalculateLayoutInputVertical","ac_meth_key_1_209":"NameRequest82","ac_meth_val_1_209":"get_minWidth","ac_meth_key_1_210":"NameRequest83","ac_meth_val_1_210":"get_preferredWidth","ac_meth_key_1_211":"NameRequest84","ac_meth_val_1_211":"get_flexibleWidth","ac_meth_key_1_212":"NameRequest85","ac_meth_val_1_212":"get_minHeight","ac_meth_key_1_213":"NameRequest86","ac_meth_val_1_213":"get_preferredHeight","ac_meth_key_1_214":"NameRequest87","ac_meth_val_1_214":"get_flexibleHeight","ac_meth_key_1_215":"NameRequest88","ac_meth_val_1_215":"get_layoutPriority","ac_meth_key_1_216":"NameRequest89","ac_meth_val_1_216":"SetGlobalPointSize","ac_meth_key_1_217":"Placeholder0","ac_meth_val_1_217":"get_materialForRendering","ac_meth_key_1_218":"Placeholder1","ac_meth_val_1_218":"get_autoSizeTextContainer","ac_meth_key_1_219":"Placeholder2","ac_meth_val_1_219":"set_autoSizeTextContainer","ac_meth_key_1_220":"Placeholder3","ac_meth_val_1_220":"get_mesh","ac_meth_key_1_221":"Placeholder4","ac_meth_val_1_221":"get_canvasRenderer","ac_meth_key_1_222":"Placeholder5","ac_meth_val_1_222":"CalculateLayoutInputHorizontal","ac_meth_key_1_223":"Placeholder6","ac_meth_val_1_223":"CalculateLayoutInputVertical","ac_meth_key_1_224":"Placeholder7","ac_meth_val_1_224":"SetVerticesDirty","ac_meth_key_1_225":"Placeholder8","ac_meth_val_1_225":"SetLayoutDirty","ac_meth_key_1_226":"Placeholder9","ac_meth_val_1_226":"SetMaterialDirty","ac_meth_key_1_227":"Placeholder10","ac_meth_val_1_227":"SetAllDirty","ac_meth_key_1_228":"Placeholder11","ac_meth_val_1_228":"get_maskOffset","ac_meth_key_1_229":"Placeholder12","ac_meth_val_1_229":"RecalculateClipping","ac_meth_key_1_230":"Placeholder13","ac_meth_val_1_230":"UpdateMeshPadding","ac_meth_key_1_231":"Placeholder14","ac_meth_val_1_231":"GetTextInfo","ac_meth_key_1_232":"Placeholder15","ac_meth_val_1_232":"ClearMesh","ac_meth_key_1_233":"Placeholder16","ac_meth_val_1_233":"UpdateVertexData","ac_meth_key_1_234":"Placeholder17","ac_meth_val_1_234":"UpdateFontAsset","ac_meth_key_1_235":"Placeholder18","ac_meth_val_1_235":"ComputeMarginSize","ac_meth_1":"IntroductionCompleted","ac_paramT_1":0,"ac_methIndex_1":2,"ac_pString_1":null,"ac_pBool_1":false,"ac_pInt_1":0,"ac_pFloat_1":0,"ac_oSet_1":1,"ac_oAct_1":-1,"ac_ovrStartNode_1":-1,"ac_renameDialogue_1":"","ac_more_1":false}